villagewars_package/__init__.py
villagewars_package/1.5.4/README.txt
villagewars_package/1.5.4/cheats.txt
villagewars_package/1.5.4/main.pyw
villagewars_package/1.5.4/assets/Achievement.png
villagewars_package/1.5.4/assets/BG_Sand.png
villagewars_package/1.5.4/assets/BG_SciFi.png
villagewars_package/1.5.4/assets/BtnPlay.png
villagewars_package/1.5.4/assets/BtnPlay_hov.png
villagewars_package/1.5.4/assets/BtnReset.png
villagewars_package/1.5.4/assets/BtnSignin.png
villagewars_package/1.5.4/assets/BtnSignup.png
villagewars_package/1.5.4/assets/Button.png
villagewars_package/1.5.4/assets/Crate.png
villagewars_package/1.5.4/assets/CrateRubble.png
villagewars_package/1.5.4/assets/Crate_hurt.png
villagewars_package/1.5.4/assets/CreatingAcount.png
villagewars_package/1.5.4/assets/Disconnected.png
villagewars_package/1.5.4/assets/Done.png
villagewars_package/1.5.4/assets/Drop.png
villagewars_package/1.5.4/assets/DropSmall.png
villagewars_package/1.5.4/assets/Edit.png
villagewars_package/1.5.4/assets/Enemy_01.png
villagewars_package/1.5.4/assets/Enemy_02.png
villagewars_package/1.5.4/assets/Enemy_03.png
villagewars_package/1.5.4/assets/Enemy_04.png
villagewars_package/1.5.4/assets/Enemy_05.png
villagewars_package/1.5.4/assets/Enemy_05_hurt.png
villagewars_package/1.5.4/assets/LargeExplosion1.png
villagewars_package/1.5.4/assets/LargeExplosion2.png
villagewars_package/1.5.4/assets/LargeExplosion3.png
villagewars_package/1.5.4/assets/Setting.png
villagewars_package/1.5.4/assets/Setting_walls.png
villagewars_package/1.5.4/assets/SigningIn.png
villagewars_package/1.5.4/assets/SmallExplosion1.png
villagewars_package/1.5.4/assets/SmallExplosion2.png
villagewars_package/1.5.4/assets/SmallExplosion3.png
villagewars_package/1.5.4/assets/SplashLarge1.png
villagewars_package/1.5.4/assets/SplashLarge2.png
villagewars_package/1.5.4/assets/SplashLarge3.png
villagewars_package/1.5.4/assets/Startgame_btn.png
villagewars_package/1.5.4/assets/Startgame_btn_locked.png
villagewars_package-1.5.4.dist-info/METADATA
villagewars_package-1.5.4.dist-info/WHEEL
villagewars_package-1.5.4.dist-info/licenses/LICENSE
villagewars_package-1.5.4.dist-info/RECORD
